codecov_validator/__init__.py
codecov_validator/ccv.py
tests/__init__.py
tests/test_ccv.py
codecov_validator-1.0.1.dist-info/LICENSE
codecov_validator-1.0.1.dist-info/METADATA
codecov_validator-1.0.1.dist-info/WHEEL
codecov_validator-1.0.1.dist-info/entry_points.txt
codecov_validator-1.0.1.dist-info/top_level.txt
codecov_validator-1.0.1.dist-info/RECORD
