Metadata-Version: 2.1
Name: codecov-validator
Version: 1.0.1
Summary: Validates the codecov.yml configuration file.
Home-page: https://github.com/mashi/codecov-validator
Author: mashi
Author-email: 59000162+mashi@users.noreply.github.com
License: UNKNOWN
Project-URL: Bug Tracker, https://github.com/mashi/codecov-validator/issues
Platform: UNKNOWN
Classifier: Programming Language :: Python :: 3
Classifier: License :: OSI Approved :: MIT License
Classifier: Operating System :: OS Independent
Requires-Python: >=3.7
License-File: LICENSE
Requires-Dist: requests (~=2.26.0)
Requires-Dist: click (~=8.0.0)
